Metadata-Version: 2.1
Name: wasmedge-py
Version: 0.0.1
Summary: Wasm Edge
Home-page: UNKNOWN
Author: Wasmer Engineering
Author-email: engineering@wasmer.io
License: UNKNOWN
Platform: UNKNOWN
Classifier: Programming Language :: Python :: 3
